{"trial_id": "085ab52555429a99e34507e8f672ce86", "hyperparameters": {"space": [{"class_name": "Int", "config": {"name": "units", "default": null, "conditions": [], "min_value": 1, "max_value": 100, "step": 1, "sampling": null}}, {"class_name": "Choice", "config": {"name": "learning_rate", "default": 0.01, "conditions": [], "values": [0.01, 0.001, 0.0001], "ordered": true}}], "values": {"units": 20, "learning_rate": 0.001, "tuner/epochs": 4, "tuner/initial_epoch": 2, "tuner/bracket": 5, "tuner/round": 1, "tuner/trial_id": "63062e5bc107857b944138707e5388c3"}}, "metrics": {"metrics": {"loss": {"direction": "min", "observations": [{"value": [0.020853355526924133], "step": 0}]}, "mean_squared_error": {"direction": "min", "observations": [{"value": [0.020853355526924133], "step": 0}]}, "val_loss": {"direction": "min", "observations": [{"value": [0.03421445190906525], "step": 0}]}, "val_mean_squared_error": {"direction": "min", "observations": [{"value": [0.03421445190906525], "step": 0}]}}}, "score": 0.03421445190906525, "best_step": 0, "status": "COMPLETED"}